unid/.DS_Store
unid/__init__.py
unid-0.0.0.dist-info/LICENSE
unid-0.0.0.dist-info/WHEEL
unid-0.0.0.dist-info/METADATA
unid-0.0.0.dist-info/RECORD
