Metadata-Version: 2.1
Name: unid
Version: 0.0.0
Summary: unid 0.0.0
Author: jcov28
Classifier: License :: OSI Approved :: MIT License
Project-URL: Home, https://unid.readthedocs.io/en/latest/index.html
